{
  "title": "Online Shoppers Purchasing Intention ",
  "description": "Dataset for real-time prediction of online shoppers purchasing intention.",
  "modelCategory": "binary_classification",
  "schemaVersion": 1.0,
  "inputDataFormat": "CSV",
  "encoding": "utf-8",
  "id": {
    "name": "id",
    "description": "unique session id"
  },
  "target": {
    "name": "Revenue",
    "description": "Binary variable indicating visitor session ending in shopping (1) or not (0)",
    "classes": [
      "0",
      "1"
    ]
  },
  "features": [
    {
      "name": "Administrative",
      "description": "Number of different \"Administrative\" pages visited in the session",
      "dataType": "NUMERIC",
      "example": 0,
      "nullable": false
    },
    {
      "name": "Administrative_Duration",
      "description": "Total time spent on \"Administrative\" pages in the session",
      "dataType": "NUMERIC",
      "example": 0.0,
      "nullable": false
    },
    {
      "name": "Informational",
      "description": "Number of different \"Informational\" pages visited in the session",
      "dataType": "NUMERIC",
      "example": 0,
      "nullable": false
    },
    {
      "name": "Informational_Duration",
      "description": "Total time spent on \"Informational\" pages in the session",
      "dataType": "NUMERIC",
      "example": 0.0,
      "nullable": false
    },
    {
      "name": "ProductRelated",
      "description": "Number of different \"ProductRelated\" pages visited in the session",
      "dataType": "NUMERIC",
      "example": 1,
      "nullable": false
    },
    {
      "name": "ProductRelated_Duration",
      "description": "Total time spent on \"ProductRelated\" pages in the session",
      "dataType": "NUMERIC",
      "example": 0.0,
      "nullable": false
    },
    {
      "name": "BounceRates",
      "description": "Bounce Rate metric from Google Analytics - refers to percentage of visitors who enter the site from that page and then leave (\"bounce\") without triggering any other requests to the analytics server during that session",
      "dataType": "NUMERIC",
      "example": 0.2,
      "nullable": false
    },
    {
      "name": "ExitRates",
      "description": "Exit Rate metric from Google Analytics. The value of \"Exit Rate\" feature for a specific web page is calculated as for all pageviews to the page, the percentage that were the last in the session.",
      "dataType": "NUMERIC",
      "example": 0.2,
      "nullable": false
    },
    {
      "name": "PageValues",
      "description": "Page Value metric from google Analytics - represents the average value for a web page that a user visited before completing an e-commerce transaction",
      "dataType": "NUMERIC",
      "example": 0.0,
      "nullable": false
    },
    {
      "name": "SpecialDay",
      "description": "Indicates the closeness of the site visiting time to a specific special day (e.g. Mother's Day, Valentine's Day) in which the sessions are more likely to be finalized with transaction",
      "dataType": "NUMERIC",
      "example": 0.0,
      "nullable": false
    },
    {
      "name": "Month",
      "description": "Month of the year",
      "dataType": "CATEGORICAL",
      "categories": [
        "Aug",
        "Dec",
        "Feb",
        "Jul",
        "June",
        "Mar",
        "May",
        "Nov",
        "Oct",
        "Sep"
      ],
      "nullable": false
    },
    {
      "name": "OperatingSystems",
      "description": "Operating system of the visitor",
      "dataType": "CATEGORICAL",
      "categories": [
        1,
        2,
        3,
        4,
        5,
        6,
        7,
        8
      ],
      "nullable": false
    },
    {
      "name": "Browser",
      "description": "Browser type of the visitor",
      "dataType": "CATEGORICAL",
      "categories": [
        1,
        10,
        11,
        12,
        13,
        2,
        3,
        4,
        5,
        6,
        7,
        8,
        9
      ],
      "nullable": false
    },
    {
      "name": "Region",
      "description": "Region of the visitor",
      "dataType": "CATEGORICAL",
      "categories": [
        1,
        2,
        3,
        4,
        5,
        6,
        7,
        8,
        9
      ],
      "nullable": false
    },
    {
      "name": "TrafficType",
      "description": "Traffic type (categories 1 to 20) - information of types not provided in dataset",
      "dataType": "CATEGORICAL",
      "categories": [
        1,
        10,
        11,
        12,
        13,
        14,
        15,
        16,
        17,
        18,
        19,
        2,
        20,
        3,
        4,
        5,
        6,
        7,
        8,
        9
      ],
      "nullable": false
    },
    {
      "name": "VisitorType",
      "description": "Returning or new visitor",
      "dataType": "CATEGORICAL",
      "categories": [
        "New_Visitor",
        "Other",
        "Returning_Visitor"
      ],
      "nullable": false
    },
    {
      "name": "Weekend",
      "description": "Is the session on weekend or weekday",
      "dataType": "CATEGORICAL",
      "categories": [
        0,
        1
      ],
      "nullable": false
    }
  ]
}